{"seed": 672808120, "moves": {"1": "W", "3": "NONE", "6": "W", "8": "NONE", "11": "W", "12": "NONE", "17": "W", "18": "NONE", "22": "W", "26": "E", "28": "NONE", "33": "W", "34": "N", "38": "NONE", "39": "W", "40": "NONE", "42": "E", "43": "S", "49": "NONE", "51": "E", "52": "W", "54": "E", "56": "NONE", "60": "E", "61": "NONE", "64": "E", "65": "NONE", "78": "E", "79": "NONE", "81": "E", "82": "NONE", "87": "E", "88": "NONE", "91": "W", "92": "NONE", "97": "W", "98": "NONE", "100": "W", "102": "NONE", "105": "W", "107": "NONE", "114": "W", "118": "E", "120": "NONE", "123": "W", "124": "NONE", "125": "N", "128": "NONE", "130": "W", "139": "NONE", "140": "E", "154": "NONE", "156": "N", "157": "NONE", "161": "S", "162": "NONE", "175": "W", "187": "NONE", "188": "E", "200": "N", "202": "NONE", "217": "E", "218": "NONE", "223": "E", "225": "NONE", "228": "S", "237": "E", "241": "NONE", "248": "N", "255": "W", "257": "N", "260": "E", "265": "NONE", "270": "S", "272": "ES", "273": "E", "274": "SE", "276": "E", "279": "NONE", "282": "W", "283": "NONE", "289": "S", "290": "NONE", "305": "E", "307": "S", "310": "NONE", "311": "N", "314": "W", "316": "NONE", "319": "E", "321": "N", "328": "NW", "329": "W", "330": "NONE", "339": "S", "342": "SE", "343": "E", "345": "S", "348": "N", "352": "NONE", "354": "S", "355": "NONE", "359": "S", "360": "NONE", "383": "S", "385": "NONE", "392": "E", "395": "NONE", "398": "S", "399": "NONE", "414": "N", "415": "NONE", "422": "W", "423": "NONE", "426": "E", "430": "NONE", "448": "E", "449": "NONE", "450": "S", "451": "NONE", "454": "N", "455": "NONE", "461": "E", "463": "NONE", "467": "E", "468": "NONE", "469": "S", "474": "NONE", "475": "E", "477": "NONE", "482": "E", "483": "NONE", "484": "N", "486": "W", "488": "NONE", "489": "N", "490": "NONE", "491": "E", "492": "NONE", "494": "N", "495": "NONE", "497": "E", "498": "NONE", "499": "N", "503": "E", "504": "NONE", "505": "S", "513": "E", "514": "NONE", "515": "N", "518": "NONE", "519": "E", "520": "NONE", "521": "N", "525": "E", "527": "S", "535": "E", "536": "NONE", "543": "S", "544": "NONE", "675": "S", "682": "NONE", "684": "N", "688": "NONE", "692": "N", "694": "NONE", "695": "W", "702": "S", "704": "NONE", "709": "S", "710": "NONE", "877": "N", "878": "NONE", "909": "S", "911": "NONE", "912": "N", "913": "NONE", "921": "S", "922": "NONE", "934": "N", "935": "NONE", "937": "S", "939": "NONE", "948": "N", "950": "NONE", "951": "S", "952": "NONE", "960": "N", "961": "NONE", "966": "S", "967": "NONE", "974": "N", "975": "NONE", "981": "S", "982": "NONE", "984": "N", "985": "NONE", "994": "S", "996": "NONE", "1006": "N", "1007": "NONE", "1008": "S", "1009": "NONE", "1012": "W", "1014": "NONE", "1024": "W", "1025": "NONE", "1027": "S"}, "last_tick": 1027, "result": {"color": "BLUE", "p": [11, 19, 0], "score": 1480, "tick": 1028}}