{"seed": 0, "moves": {"1": "W", "5": "S", "17": "E", "21": "S", "29": "E", "31": "S", "35": "W", "37": "S", "39": "N", "41": "W", "43": "N", "47": "E", "49": "N", "61": "W", "65": "N", "73": "W", "85": "N", "93": "E", "105": "N", "117": "W", "121": "N", "129": "E", "133": "S", "135": "E", "141": "N", "145": "S", "149": "W", "155": "N", "157": "W", "161": "S", "169": "E", "173": "S", "181": "E", "185": "S", "189": "W", "205": "N", "209": "E", "213": "S", "217": "W", "221": "S", "229": "E", "241": "S", "253": "E", "257": "S", "271": "W", "279": "N", "285": "W", "289": "N", "297": "W", "301": "N", "305": "E", "309": "S", "321": "W", "323": "S", "331": "W", "339": "N", "343": "S", "347": "E", "353": "N", "361": "E", "367": "S", "373": "E", "383": "N", "397": "W", "401": "N", "413": "W", "433": "S", "445": "W", "449": "N", "453": "E", "457": "N", "465": "W", "469": "N", "481": "E", "485": "S", "489": "N", "501": "E", "503": "N", "505": "E", "513": "N", "519": "W", "521": "N", "523": "W", "529": "S", "533": "W", "537": "S", "539": "W", "545": "S", "549": "W", "551": "S", "553": "W", "555": "S", "561": "W", "565": "S", "569": "E", "573": "W", "575": "E", "577": "W", "579": "E", "581": "W", "585": "N", "589": "E", "593": "N", "601": "E", "603": "N", "609": "W", "617": "N", "619": "W", "627": "S", "629": "W", "633": "SW", "635": "S", "639": "N", "643": "E", "649": "N", "651": "E", "659": "S", "661": "E", "669": "S", "671": "E", "681": "N", "685": "E", "689": "N", "691": "E", "695": "S", "697": "E", "699": "S", "705": "W", "713": "S", "715": "W", "717": "S", "725": "W", "729": "S", "741": "W", "753": "S", "761": "E", "765": "S", "777": "E", "779": "S", "783": "E", "787": "S", "791": "W", "807": "N", "811": "E", "815": "N", "819": "W", "823": "S", "827": "E", "829": "S", "833": "E", "841": "N", "857": "W", "861": "E", "865": "N", "869": "W", "873": "N", "881": "W", "893": "S", "897": "N", "901": "E", "905": "N", "913": "W", "917": "N", "921": "E", "925": "S", "937": "W", "941": "S", "949": "E", "953": "S", "957": "W", "961": "N", "963": "S", "979": "W", "981": "E", "983": "N", "1009": "W"}, "last_tick": 1009, "result": {"color": "BLUE", "p": [1, 16, 0], "score": 3490, "tick": 1010}}