{"seed": 200652153, "moves": {"1": "W", "11": "WN", "13": "N", "17": "S", "19": "SW", "21": "W", "26": "WN", "27": "N", "43": "NW", "44": "W", "48": "WN", "49": "N", "53": "NW", "54": "W", "61": "WS", "63": "S", "68": "SW", "69": "W", "73": "WS", "75": "S", "77": "NONE", "78": "W", "79": "WS", "80": "S", "81": "NONE", "82": "E", "84": "S", "85": "SW", "86": "W", "87": "E", "89": "N", "94": "NE", "95": "E", "100": "NONE", "117": "E", "119": "N", "123": "NE", "124": "E", "126": "N", "129": "E", "131": "N", "145": "NW", "146": "W", "156": "WN", "161": "W", "164": "WN", "170": "W", "175": "S", "181": "N", "182": "NW", "183": "W", "185": "E", "186": "N", "192": "W", "194": "N", "196": "NW", "197": "W", "202": "WS", "203": "S", "204": "N", "206": "E", "212": "S", "214": "E", "216": "NONE", "217": "E", "219": "S", "221": "E", "223": "S", "228": "E", "233": "NONE", "234": "S", "236": "E", "240": "ES", "241": "S", "243": "E", "255": "EN", "258": "E", "261": "ES", "262": "S", "266": "N", "267": "E", "270": "W", "271": "WN", "272": "N", "274": "NW", "275": "W", "278": "NONE", "281": "W", "282": "WS", "283": "S", "287": "W", "291": "WS", "292": "S", "307": "E", "309": "ES", "310": "S", "311": "E", "313": "ES", "314": "S", "318": "E", "322": "ES", "323": "S", "333": "NONE", "337": "S", "338": "NONE", "341": "S", "346": "SE", "347": "E", "352": "EN", "353": "N", "359": "S", "363": "SW", "365": "W", "372": "N", "374": "NONE", "382": "E", "384": "N", "386": "NONE", "390": "N", "393": "NONE", "397": "N", "408": "W", "412": "N", "418": "NW", "419": "W", "420": "WN", "421": "N", "422": "W", "424": "N", "440": "NW", "441": "W", "450": "WN", "451": "N", "454": "NW", "455": "W", "459": "S", "463": "N", "465": "W", "467": "E", "468": "EN", "469": "N", "470": "E", "476": "S", "481": "E", "482": "ES", "483": "S", "491": "N", "493": "W", "495": "E", "496": "EN", "497": "N", "500": "NE", "501": "E", "513": "N", "517": "NE", "519": "E", "527": "EN", "530": "E", "534": "EN", "537": "E", "542": "EN", "544": "E", "546": "ES", "547": "S", "552": "N", "553": "E", "555": "NONE", "556": "W", "558": "N", "559": "NW", "560": "W", "563": "S", "566": "SW", "567": "W", "572": "S", "575": "W", "583": "S", "590": "SW", "591": "W", "597": "S", "610": "NONE", "612": "W", "614": "S", "616": "W", "618": "S", "623": "SW", "624": "W", "629": "WS", "630": "S", "638": "SW", "639": "W", "643": "NONE", "644": "N", "646": "E", "648": "NONE", "651": "E", "653": "NONE", "668": "N", "672": "E", "674": "N", "676": "E", "681": "NONE", "683": "S", "690": "SE", "691": "E", "694": "W", "696": "NONE", "697": "S", "702": "SW", "704": "W", "710": "E", "718": "EN", "719": "N", "724": "E", "730": "EN", "731": "N", "733": "W", "735": "S", "737": "NONE", "739": "N", "741": "NONE", "747": "E", "749": "N", "753": "NE", "754": "E", "758": "ES", "759": "S", "769": "NONE", "771": "S", "778": "SE", "779": "E", "784": "N", "791": "S", "793": "N", "797": "S", "804": "NONE", "806": "W", "812": "N", "814": "NONE", "825": "N", "841": "W", "843": "NONE", "845": "W", "846": "WN", "847": "N", "852": "NONE", "853": "S", "855": "W", "857": "NONE", "858": "N", "861": "NW", "862": "W", "863": "N", "877": "NE", "878": "E", "884": "EN", "885": "E", "889": "EN", "895": "E", "896": "NONE", "899": "E", "903": "N", "906": "NE", "907": "E", "910": "ES", "911": "S", "917": "N", "919": "E", "921": "NONE", "922": "W", "923": "WN", "924": "N", "929": "NE", "930": "E", "931": "N", "933": "NE", "934": "E", "939": "ES", "940": "S", "942": "N", "944": "W", "949": "NONE", "950": "S", "952": "W", "954": "NONE", "956": "S", "958": "W", "962": "S", "964": "W", "967": "WS", "968": "S", "975": "SW", "976": "W", "986": "N", "988": "NONE", "996": "N", "1000": "NONE", "1003": "N", "1005": "NONE", "1017": "N", "1022": "NW", "1023": "W", "1027": "E", "1034": "W", "1038": "NONE", "1040": "S", "1041": "NONE", "1045": "S", "1049": "NONE", "1050": "E", "1056": "NONE", "1058": "N", "1060": "E", "1065": "N", "1069": "W", "1071": "S", "1073": "E", "1075": "S", "1077": "W", "1079": "N", "1081": "W", "1083": "S", "1085": "SE", "1086": "E", "1087": "ES", "1088": "S", "1089": "W", "1091": "NONE", "1093": "S", "1095": "W", "1097": "NONE", "1100": "W", "1102": "NONE", "1108": "W", "1110": "NONE", "1111": "N", "1112": "NW", "1113": "W", "1114": "NONE", "1115": "S", "1117": "NONE", "1119": "S", "1128": "NONE", "1143": "W", "1149": "WN", "1151": "W", "1155": "S", "1159": "N", "1160": "NW", "1161": "W", "1163": "E", "1164": "EN", "1165": "N", "1167": "E", "1170": "S", "1172": "E", "1178": "S", "1193": "NONE", "1198": "W", "1199": "NONE", "1203": "E", "1205": "NONE", "1210": "E", "1212": "NONE", "1213": "S", "1215": "W", "1217": "N", "1219": "W", "1221": "NONE", "1249": "E", "1250": "S", "1253": "NONE", "1255": "S", "1258": "NONE", "1261": "S", "1266": "W", "1269": "NONE", "1270": "N", "1274": "W", "1280": "NONE", "1282": "E", "1286": "EN", "1287": "N", "1290": "NONE", "1291": "W", "1292": "WN", "1293": "N", "1297": "E", "1299": "S", "1305": "SW", "1306": "W", "1309": "N", "1310": "NW", "1311": "W", "1317": "S", "1319": "NONE", "1322": "W", "1324": "NONE", "1325": "S", "1327": "NONE", "1330": "E", "1333": "NONE", "1340": "W", "1341": "WN", "1342": "N", "1345": "NE", "1346": "E", "1350": "ES", "1351": "S", "1359": "SE", "1360": "E", "1361": "S", "1366": "NONE", "1367": "W", "1369": "NONE", "1371": "S", "1373": "NONE", "1374": "W", "1376": "NONE", "1380": "N", "1381": "NW", "1382": "W", "1386": "S", "1388": "SW", "1389": "W", "1393": "N", "1394": "NW", "1395": "W", "1398": "S", "1400": "SW", "1401": "W", "1408": "E", "1413": "N", "1415": "NE", "1416": "E", "1419": "S", "1421": "SE", "1422": "E", "1426": "N", "1427": "NE", "1428": "E", "1435": "EN", "1436": "N", "1438": "NONE", "1455": "N", "1456": "NE", "1457": "E", "1462": "EN", "1470": "E", "1474": "ES", "1475": "S", "1482": "NONE", "1486": "S", "1489": "NONE", "1493": "S", "1498": "SE", "1499": "E", "1504": "N", "1511": "S", "1516": "SW", "1518": "W", "1523": "NONE", "1524": "N", "1526": "NONE", "1527": "N", "1530": "NONE", "1533": "N", "1543": "NW", "1544": "W", "1548": "WN", "1549": "N", "1554": "NONE", "1568": "W", "1570": "NONE", "1574": "S", "1575": "W", "1577": "N", "1590": "NONE", "1591": "W", "1593": "N", "1595": "E", "1597": "NONE", "1598": "N", "1599": "NE", "1600": "E", "1601": "NONE", "1602": "S", "1606": "NONE", "1607": "W", "1608": "NONE", "1609": "S", "1611": "E", "1615": "W", "1616": "WN", "1617": "N", "1624": "NE", "1625": "E", "1628": "ES", "1629": "S", "1635": "N", "1637": "E", "1639": "W", "1640": "WN", "1641": "N", "1646": "NE", "1647": "E", "1651": "N", "1654": "NE", "1655": "E", "1659": "S", "1663": "N", "1665": "E", "1667": "W", "1668": "WN", "1669": "N", "1676": "E", "1680": "W", "1682": "NONE", "1683": "W", "1685": "WS", "1686": "S", "1690": "NONE", "1691": "W", "1695": "S", "1697": "NONE", "1699": "W", "1702": "S", "1703": "SW", "1704": "W", "1711": "NONE", "1712": "S", "1714": "W", "1719": "WN", "1720": "N", "1724": "NW", "1725": "W", "1733": "WN", "1734": "N", "1738": "W", "1742": "N", "1745": "NW", "1746": "W", "1750": "S", "1754": "N", "1756": "NW", "1757": "W", "1758": "E", "1760": "NONE", "1764": "W", "1766": "S", "1768": "W", "1770": "E", "1772": "N", "1773": "NE", "1774": "E", "1777": "ES", "1778": "S", "1780": "E", "1783": "ES", "1784": "S", "1787": "NONE", "1790": "E", "1793": "S", "1796": "E", "1800": "S", "1806": "E", "1811": "N", "1816": "NONE", "1827": "N", "1832": "NONE", "1835": "W", "1842": "NONE", "1845": "N", "1846": "NONE", "1847": "W", "1850": "N", "1854": "E", "1856": "NONE", "1857": "S", "1858": "SW", "1859": "W", "1861": "S", "1862": "SE", "1863": "E", "1865": "N", "1867": "E", "1869": "S", "1871": "W", "1873": "S", "1875": "E", "1877": "NONE", "1882": "E", "1884": "NONE", "1893": "E", "1895": "NONE", "1902": "N", "1904": "E", "1906": "S", "1908": "NONE", "1921": "S", "1923": "NONE", "1931": "S", "1935": "NONE", "1937": "S", "1944": "NONE", "1947": "S", "1949": "NONE", "1950": "E", "1951": "NONE", "1952": "S", "1955": "W", "1957": "NONE", "1960": "E", "1962": "NONE", "1963": "N", "1965": "W", "1970": "NONE", "1972": "E", "1975": "NONE", "1978": "S", "1985": "NONE", "1987": "S", "2001": "SW", "2002": "W", "2003": "S", "2007": "SW", "2008": "W", "2019": "NONE", "2024": "E", "2031": "NONE", "2033": "N", "2039": "E", "2044": "EN", "2046": "N", "2052": "NONE", "2057": "E", "2061": "NONE", "2062": "S", "2068": "NONE", "2071": "S", "2073": "NONE", "2078": "S", "2082": "NONE", "2086": "S", "2093": "SW", "2095": "W", "2106": "NONE", "2109": "W", "2111": "NONE", "2114": "W", "2116": "E", "2140": "NONE", "2141": "N", "2145": "S", "2150": "SW", "2151": "W", "2166": "NONE", "2168": "W", "2174": "NONE", "2177": "E", "2198": "NONE", "2200": "N", "2202": "NONE", "2204": "N", "2205": "NONE", "2206": "S", "2208": "N", "2210": "S", "2214": "SW", "2215": "W", "2235": "NONE", "2257": "W", "2259": "NONE", "2261": "E", "2280": "NONE", "2282": "E", "2286": "NONE", "2287": "N", "2290": "NONE", "2291": "S", "2294": "SW", "2296": "W", "2312": "NONE", "2313": "W", "2315": "NONE", "2318": "W", "2320": "NONE", "2323": "W", "2329": "S", "2331": "N", "2332": "NE", "2333": "E", "2349": "NONE", "2351": "W", "2378": "NONE", "2382": "E", "2438": "NONE", "2439": "S", "2441": "E"}, "last_tick": 2441, "result": {"color": "BLUE", "p": [30, 30, 0], "score": 0, "tick": 2440}}