{"seed": 1140198761, "moves": {"1": "W", "9": "N", "12": "NONE", "13": "W", "16": "NONE", "26": "N", "27": "NONE", "35": "N", "36": "NONE", "37": "N", "38": "NONE", "40": "S", "41": "NONE", "60": "W", "62": "E", "63": "NONE", "66": "W", "69": "NONE", "72": "S", "73": "NONE", "74": "N", "78": "W", "81": "NONE", "83": "S", "84": "NONE", "85": "W", "86": "NONE", "87": "W", "88": "NONE", "92": "S", "93": "NONE", "95": "E", "96": "NONE", "98": "S", "99": "NONE", "100": "N", "103": "NONE", "110": "E", "111": "NONE", "121": "N", "122": "NONE", "123": "E", "126": "NONE", "127": "S", "130": "NONE", "131": "W", "132": "NONE", "134": "E", "135": "NONE", "136": "N", "137": "NONE", "138": "E", "139": "NONE", "141": "E", "143": "NONE", "150": "W", "153": "NONE", "154": "S", "155": "NONE", "156": "W", "158": "S", "159": "NONE", "160": "N", "161": "NONE", "162": "E", "163": "NONE", "164": "N", "165": "NONE", "166": "E", "169": "NONE", "170": "S", "173": "NONE", "174": "E", "176": "NONE", "180": "E", "181": "NONE", "182": "N", "187": "NONE", "188": "E", "191": "NONE", "193": "N", "194": "NONE", "205": "N", "208": "NONE", "213": "E", "214": "NONE", "215": "E", "218": "W", "225": "NONE", "226": "S", "231": "NONE", "234": "W", "237": "NONE", "243": "N", "258": "NONE", "263": "E", "266": "W", "270": "NONE", "272": "E", "283": "W", "298": "NW", "299": "W", "305": "NW", "306": "W", "315": "E", "325": "S", "329": "E", "330": "S", "337": "ES", "338": "S", "342": "NONE", "343": "W", "344": "S", "348": "W", "353": "N", "356": "NONE", "361": "N", "362": "NONE", "367": "W", "368": "NONE", "394": "W", "395": "NONE", "481": "W", "483": "S", "485": "W", "488": "NONE", "492": "N", "493": "NONE", "495": "S", "496": "NONE", "508": "N", "509": "NONE", "536": "N", "540": "NONE", "550": "E", "553": "NONE", "566": "S", "567": "NONE", "568": "E", "569": "NONE", "570": "S", "571": "E", "573": "NONE", "576": "E", "577": "S", "582": "NONE", "584": "E", "586": "NONE", "587": "S", "588": "NONE", "589": "E", "593": "NONE", "623": "N", "624": "NONE", "625": "E", "626": "NONE", "627": "N", "634": "E", "645": "NONE", "649": "E", "651": "NONE", "656": "E", "657": "NONE", "658": "S", "667": "NONE", "668": "E", "672": "SE", "673": "E", "677": "SE", "679": "E", "687": "NONE", "688": "N", "689": "NONE", "690": "E", "693": "N", "695": "E", "699": "N", "714": "W", "725": "NONE", "727": "S", "728": "NONE", "736": "N", "737": "NONE", "747": "W", "751": "NONE", "754": "E", "759": "NONE", "775": "E", "782": "NONE", "783": "S", "789": "ES", "790": "S", "804": "W", "808": "NONE", "813": "E", "814": "NONE", "816": "W", "817": "NONE", "824": "S", "827": "NONE", "834": "S", "835": "E", "840": "S", "860": "NONE", "861": "W", "877": "NONE", "878": "E", "892": "NONE", "893": "N", "896": "EN", "897": "N", "907": "NONE", "936": "S", "938": "NONE", "954": "N", "958": "NONE", "961": "S", "972": "W", "976": "NONE", "979": "N", "982": "NONE", "984": "W", "987": "NONE", "989": "N", "992": "NONE", "993": "E", "996": "NE", "997": "N", "1005": "W", "1008": "NONE", "1009": "E", "1010": "NONE", "1011": "S", "1012": "E", "1014": "S", "1020": "NONE", "1021": "W", "1025": "N", "1028": "NONE", "1033": "S", "1036": "NONE", "1040": "N", "1041": "NONE", "1053": "E", "1054": "NONE", "1055": "N", "1056": "NONE", "1057": "E", "1058": "NONE", "1059": "N", "1063": "W", "1066": "NONE", "1067": "S", "1070": "NONE", "1071": "E", "1074": "NONE", "1075": "S", "1076": "NONE", "1079": "W", "1080": "N", "1085": "NONE", "1087": "S", "1091": "NONE", "1154": "S", "1159": "WS", "1160": "W", "1172": "E", "1185": "N", "1189": "NONE", "1190": "W", "1191": "N", "1196": "E", "1202": "NONE", "1203": "S", "1207": "NONE", "1208": "N", "1220": "W", "1223": "N", "1228": "W", "1232": "NONE", "1233": "S", "1234": "W", "1238": "N", "1243": "NONE", "1254": "N", "1255": "NONE", "1256": "N", "1257": "NONE", "1264": "N", "1265": "NONE", "1267": "W", "1270": "NONE", "1273": "W", "1274": "NONE", "1275": "E", "1280": "NONE", "1295": "N", "1296": "NONE", "1297": "E", "1298": "NONE", "1299": "N", "1300": "E", "1306": "NONE", "1309": "S", "1310": "NONE", "1311": "N", "1313": "W", "1318": "NONE", "1321": "S", "1322": "NONE", "1323": "W", "1324": "NONE", "1325": "S", "1336": "NONE", "1337": "W", "1338": "NONE", "1342": "W", "1343": "S", "1355": "NONE", "1358": "S", "1359": "NONE", "1360": "W", "1365": "NONE", "1366": "S", "1374": "NONE", "1375": "E", "1378": "NONE", "1382": "E", "1384": "NONE", "1386": "E", "1401": "SE", "1402": "S", "1415": "NONE", "1420": "S", "1424": "SW", "1425": "W", "1437": "NONE", "1441": "E", "1454": "NE", "1455": "N", "1465": "NONE", "1467": "S", "1478": "NONE", "1489": "N", "1500": "NONE", "1522": "S", "1527": "NONE", "1546": "S", "1551": "NONE", "1557": "N", "1567": "NONE", "1606": "S", "1615": "WS", "1616": "W", "1620": "N", "1623": "W", "1632": "NONE", "1636": "E", "1637": "NONE", "1638": "N", "1639": "NONE", "1641": "E", "1642": "NONE", "1646": "E", "1647": "NONE", "1649": "N", "1650": "NE", "1660": "N", "1661": "NONE", "1666": "W", "1667": "N", "1670": "NONE", "1673": "N", "1679": "NONE", "1687": "N", "1688": "W", "1691": "NONE", "1692": "E", "1693": "NONE", "1697": "S", "1704": "NONE", "1709": "E", "1710": "NONE", "1711": "S", "1712": "NONE", "1713": "E", "1714": "SE", "1715": "S", "1719": "W", "1740": "N", "1742": "W", "1747": "NW", "1749": "W", "1761": "NONE", "1769": "E", "1772": "N", "1794": "NONE", "1796": "S", "1797": "NONE", "1798": "N", "1801": "W", "1807": "SW", "1808": "S", "1812": "ES", "1813": "SE", "1814": "S", "1823": "NONE", "1826": "N", "1833": "W", "1835": "N", "1839": "NONE", "1841": "W", "1847": "NONE", "1854": "W", "1862": "S", "1869": "NONE", "1870": "E", "1871": "NONE", "1872": "S", "1878": "W", "1880": "S", "1891": "NONE", "1896": "E", "1899": "SE", "1902": "E", "1905": "NONE", "1906": "N", "1909": "EN", "1910": "NE", "1912": "N", "1914": "EN", "1915": "N", "1918": "EN", "1919": "E", "1925": "NONE", "1926": "N", "1948": "NW", "1949": "W", "1961": "NONE", "1965": "S", "1969": "E", "1971": "SE", "1972": "S", "1975": "NONE", "1977": "W", "1981": "S", "1984": "NONE", "1985": "E", "1989": "SE", "1998": "S", "1999": "NONE", "2000": "N", "2004": "E", "2006": "N", "2008": "NONE", "2009": "E", "2010": "NONE", "2011": "W", "2013": "S", "2020": "NONE", "2021": "W", "2023": "SW", "2028": "S", "2029": "E", "2031": "SE", "2032": "S", "2037": "SW", "2045": "S", "2047": "NONE", "2048": "N", "2049": "E", "2055": "NE", "2056": "N", "2068": "W", "2072": "N", "2073": "WN", "2074": "NW", "2077": "W", "2079": "SW", "2082": "W", "2087": "NW", "2088": "N", "2096": "EN", "2097": "N", "2102": "E", "2113": "NONE", "2114": "N", "2130": "NONE", "2153": "E", "2154": "W", "2159": "S", "2160": "NONE", "2161": "N", "2163": "E", "2166": "NONE", "2179": "E", "2180": "NONE", "2184": "E", "2185": "NONE", "2191": "N", "2194": "NONE", "2196": "E", "2197": "NONE", "2198": "N", "2201": "E", "2203": "NONE", "2205": "W", "2207": "NONE", "2208": "S", "2209": "NONE", "2210": "W", "2214": "NONE", "2216": "S", "2220": "W", "2224": "NONE", "2227": "S", "2233": "NONE", "2255": "N", "2260": "NONE", "2262": "W", "2267": "NONE", "2271": "E", "2275": "NONE", "2279": "E", "2280": "NONE", "2281": "S", "2288": "NONE", "2289": "E", "2290": "NONE", "2291": "N", "2292": "NONE", "2293": "E", "2316": "NONE", "2321": "N", "2322": "E", "2331": "NONE", "2333": "S", "2334": "NONE", "2335": "E", "2337": "NONE", "2339": "E", "2342": "NONE", "2347": "S", "2366": "NONE", "2367": "W", "2383": "NONE", "2389": "W", "2397": "NONE", "2404": "W", "2410": "S", "2413": "NONE", "2423": "W", "2425": "NONE", "2429": "E", "2431": "NONE", "2456": "S", "2457": "E", "2461": "NONE", "2480": "N", "2483": "NONE", "2485": "S", "2489": "W", "2491": "NONE", "2496": "W", "2497": "NONE", "2498": "N", "2500": "W", "2502": "NONE", "2513": "N", "2514": "NONE", "2518": "S", "2520": "NONE", "2522": "E", "2523": "NONE", "2529": "W", "2533": "NONE", "2536": "S", "2537": "NONE", "2539": "N", "2544": "NONE", "2545": "E", "2557": "NONE", "2562": "W", "2566": "NONE", "2573": "N", "2577": "NONE", "2578": "W", "2584": "N", "2585": "NONE", "2586": "S", "2588": "E", "2592": "NONE", "2593": "S", "2596": "E", "2597": "S", "2601": "E", "2610": "NONE", "2611": "S", "2619": "W", "2620": "NONE", "2621": "S", "2628": "W", "2643": "NW", "2645": "W", "2655": "NONE", "2656": "E", "2657": "NE", "2658": "N", "2681": "W", "2687": "S", "2691": "SE", "2694": "S", "2708": "NONE", "2709": "N", "2722": "WN", "2723": "NW", "2724": "N", "2728": "E", "2735": "S", "2758": "E", "2767": "NONE", "2770": "S", "2771": "NONE", "2772": "E", "2785": "NONE", "2786": "N", "2793": "NONE", "2794": "E", "2795": "NONE", "2796": "N", "2804": "W", "2819": "S", "2825": "NONE", "2827": "W", "2828": "NONE", "2832": "E", "2834": "NONE", "2839": "S", "2840": "NONE", "2841": "E", "2844": "NONE", "2847": "W", "2848": "NONE", "2853": "W", "2854": "NONE", "2855": "N", "2857": "W", "2860": "NONE", "2862": "S", "2863": "NONE", "2866": "N", "2879": "NONE", "2883": "N", "2884": "NONE", "2885": "E", "2886": "NONE", "2887": "W", "2888": "NONE", "2891": "N", "2894": "NONE", "2896": "E", "2897": "NONE", "2898": "N", "2899": "NONE", "2900": "E", "2903": "NONE", "2906": "S", "2907": "E", "2909": "NONE", "2910": "S", "2912": "NONE", "2914": "S", "2915": "W", "2917": "S", "2919": "W", "2934": "N", "2936": "W", "2955": "N", "2970": "E", "2988": "NONE", "2990": "N", "2992": "NONE", "2993": "E", "2995": "NONE", "2996": "N", "3006": "E", "3020": "SE", "3029": "E", "3035": "SE", "3036": "E", "3041": "SE", "3042": "E", "3053": "NONE", "3054": "N", "3057": "EN", "3058": "N", "3060": "NE", "3065": "N", "3073": "NONE", "3074": "S", "3125": "WS", "3126": "SW", "3127": "W", "3151": "NW", "3152": "N", "3153": "NW", "3154": "W", "3157": "N", "3159": "W", "3167": "NONE", "3168": "S", "3171": "NONE", "3172": "N", "3189": "EN", "3190": "E", "3197": "S", "3204": "NONE", "3205": "E", "3206": "NONE", "3210": "E", "3211": "NONE"}, "last_tick": 3211, "result": {"color": "BLUE", "p": [17, 24, 0], "score": 1490, "tick": 3211}}