{"seed": 957727854, "moves": {"1": "N", "2": "NONE", "3": "E", "11": "S", "12": "NONE", "14": "N", "15": "NONE", "16": "W", "20": "NONE", "25": "N", "32": "NONE", "33": "S", "35": "NONE", "36": "W", "42": "NONE", "48": "W", "49": "N", "54": "NONE", "56": "W", "57": "NONE", "58": "N", "59": "NONE", "60": "W", "61": "NONE", "62": "E", "63": "NONE", "65": "S", "73": "NONE", "75": "W", "77": "SW", "78": "S", "85": "NONE", "86": "N", "88": "NONE", "89": "E", "92": "NE", "93": "E", "102": "NONE", "107": "W", "108": "NONE", "121": "E", "132": "S", "137": "NONE", "139": "N", "145": "W", "148": "NONE", "149": "N", "152": "NONE", "153": "S", "155": "W", "163": "NONE", "166": "E", "168": "NONE", "169": "W", "170": "NONE", "171": "S", "176": "E", "184": "NONE", "185": "S", "186": "NONE", "187": "N", "188": "W", "198": "N", "210": "W", "212": "NONE", "213": "E", "214": "NONE", "215": "S", "219": "NONE", "220": "W", "224": "N", "225": "W", "231": "NONE", "232": "E", "237": "NONE", "238": "S", "239": "NONE", "240": "E", "243": "NONE", "244": "N", "249": "NONE", "255": "S", "256": "NONE", "258": "S", "261": "NONE", "270": "S", "275": "SE", "276": "E", "286": "NONE", "289": "S", "293": "NONE", "294": "N", "295": "NONE", "298": "W", "305": "NONE", "315": "E", "327": "NONE", "337": "S", "338": "NONE", "339": "N", "341": "NONE", "346": "W", "348": "NONE", "352": "W", "361": "NONE", "364": "E", "371": "NONE", "382": "N", "389": "NONE", "391": "S", "392": "NONE", "393": "W", "400": "NONE", "404": "W", "405": "NONE", "408": "S", "409": "NONE", "412": "E", "423": "S", "430": "NONE", "431": "N", "434": "W", "445": "NONE", "447": "N", "457": "W", "461": "NONE", "468": "W", "469": "NONE", "470": "N", "477": "NONE", "479": "S", "483": "NONE", "484": "E", "491": "NONE", "502": "N", "504": "NONE", "505": "E", "515": "NONE", "522": "S", "527": "NONE", "528": "E", "530": "NONE", "533": "S", "539": "W", "542": "NONE", "549": "S", "554": "NONE", "555": "W", "556": "NONE", "557": "E", "561": "S", "562": "NONE", "563": "N", "565": "W", "567": "NONE", "575": "W", "576": "NONE", "583": "E", "585": "NONE", "589": "N", "597": "W", "598": "NONE", "599": "E", "607": "NONE", "615": "N", "617": "NONE", "620": "N", "621": "NONE", "622": "E", "625": "NONE", "627": "W", "628": "NONE", "630": "S", "636": "NONE", "637": "E", "640": "S", "649": "NONE", "651": "N", "656": "W", "664": "NONE", "673": "W", "674": "NONE", "675": "W", "676": "NONE", "680": "S", "681": "NONE", "682": "W", "683": "NONE", "685": "S", "686": "NONE", "688": "E", "691": "NONE", "694": "S", "696": "NONE", "697": "N", "698": "NONE", "699": "W", "700": "NONE", "701": "W", "704": "N", "707": "NONE", "708": "E", "710": "N", "715": "NONE", "716": "E", "723": "NONE", "735": "W", "738": "S", "745": "NONE", "746": "W", "749": "NONE", "750": "S", "754": "NONE", "756": "N", "758": "NONE", "760": "E", "766": "NONE", "767": "N", "778": "NONE", "781": "E", "787": "NONE", "790": "W", "791": "NONE", "796": "S", "799": "NONE", "801": "E", "804": "NONE", "805": "N", "806": "NONE", "807": "E", "813": "NONE", "815": "W", "821": "S", "824": "NONE", "825": "W", "836": "S", "838": "NONE", "847": "W", "848": "NONE", "853": "E", "854": "NONE", "857": "W", "858": "NONE", "859": "S", "865": "NONE", "868": "N", "869": "NONE", "871": "E", "875": "NONE", "876": "S", "877": "NONE", "878": "N", "879": "NONE", "880": "W", "884": "NONE", "885": "N", "891": "NONE", "892": "N", "893": "NONE", "895": "E", "903": "NONE", "914": "W", "915": "S", "919": "W", "923": "NONE", "925": "S", "930": "NONE", "932": "N", "936": "NONE", "938": "E", "945": "NONE", "947": "N", "967": "NONE", "969": "S", "977": "NONE", "979": "E", "980": "NONE", "982": "S", "983": "NONE", "984": "W", "985": "NONE", "989": "N", "994": "NONE", "996": "E", "997": "NONE", "998": "E", "1000": "NONE", "1002": "N", "1011": "NONE", "1013": "S", "1018": "NONE", "1019": "W", "1022": "S", "1026": "SW", "1028": "W", "1037": "NONE", "1042": "S", "1056": "NONE", "1057": "W", "1058": "NONE", "1060": "S", "1064": "NONE", "1066": "N", "1069": "NONE", "1075": "E", "1078": "NONE", "1079": "S", "1083": "NONE", "1084": "N", "1089": "NW", "1090": "W", "1093": "NONE", "1094": "N", "1097": "NONE", "1098": "E", "1100": "NONE", "1101": "N", "1108": "NONE", "1112": "N", "1114": "NONE", "1116": "N", "1119": "NONE", "1127": "W", "1128": "E", "1130": "NONE", "1131": "N", "1137": "NONE", "1141": "N", "1143": "W", "1158": "NONE", "1161": "E", "1174": "NONE", "1176": "S", "1177": "NONE", "1178": "N", "1179": "NONE", "1183": "W", "1195": "NONE", "1198": "W", "1205": "NONE", "1206": "E", "1225": "NONE", "1230": "E", "1231": "NONE", "1232": "S", "1262": "NONE", "1264": "E", "1266": "S", "1267": "NONE", "1269": "N", "1270": "NONE", "1272": "N", "1279": "NONE", "1280": "W", "1284": "NONE", "1286": "E", "1287": "NONE", "1288": "N", "1298": "NONE", "1300": "W", "1301": "N", "1305": "NONE", "1307": "E", "1308": "NONE", "1310": "N", "1315": "NONE", "1317": "N", "1319": "NONE", "1320": "W", "1321": "NONE", "1324": "E", "1325": "NONE", "1326": "S", "1354": "NONE", "1355": "W", "1356": "NONE", "1358": "E", "1359": "NONE", "1360": "S", "1364": "NONE", "1366": "N", "1393": "NONE", "1395": "N", "1397": "NONE", "1398": "W", "1399": "N", "1401": "NONE", "1405": "W", "1412": "NONE", "1415": "W", "1418": "NONE", "1421": "W", "1425": "NONE", "1427": "S", "1433": "NONE", "1434": "N", "1438": "NONE", "1439": "E", "1447": "NONE", "1449": "S", "1456": "NONE", "1457": "E", "1458": "NONE", "1459": "S", "1461": "NONE", "1462": "E", "1469": "NONE", "1471": "W", "1473": "NONE", "1475": "E", "1478": "NONE", "1479": "S", "1495": "NONE", "1498": "S", "1502": "NONE", "1503": "N", "1511": "W", "1514": "NONE", "1515": "N", "1516": "NONE", "1517": "E", "1518": "NONE", "1520": "N", "1530": "NONE", "1538": "N", "1539": "NONE", "1541": "S", "1559": "NONE", "1561": "W", "1562": "NONE", "1563": "S", "1567": "NONE", "1568": "N", "1572": "NONE", "1573": "E", "1575": "NONE", "1577": "N", "1592": "NONE", "1596": "W", "1604": "NONE", "1605": "E", "1614": "NONE", "1616": "N", "1628": "NONE", "1633": "N", "1635": "NONE", "1639": "S", "1649": "NONE", "1653": "W", "1654": "NONE", "1656": "W", "1657": "NONE", "1658": "E", "1660": "NONE", "1665": "E", "1666": "NONE", "1670": "N", "1676": "NONE", "1682": "E", "1684": "NONE", "1687": "N", "1688": "NONE", "1690": "E", "1692": "NONE", "1694": "N", "1695": "NONE", "1697": "N", "1698": "NONE", "1704": "E", "1705": "NONE", "1708": "N", "1709": "NONE", "1710": "E", "1714": "NONE", "1715": "W", "1718": "NONE", "1720": "S", "1728": "NONE", "1729": "W", "1736": "NONE", "1737": "S", "1748": "NONE", "1750": "S", "1764": "NONE", "1768": "E", "1769": "NONE", "1770": "S", "1774": "NONE", "1776": "N", "1781": "W", "1785": "S", "1792": "NONE", "1794": "N", "1804": "NONE", "1805": "E", "1806": "NONE", "1807": "N", "1816": "NONE", "1819": "S", "1833": "NONE", "1834": "W", "1835": "NONE", "1836": "S", "1842": "NONE", "1844": "N", "1846": "NONE", "1847": "E", "1849": "NONE", "1850": "N", "1865": "NONE", "1868": "E", "1870": "NONE", "1871": "N", "1876": "NONE", "1882": "N", "1888": "NONE", "1892": "S", "1898": "NONE", "1899": "W", "1902": "NONE", "1903": "E", "1907": "NONE", "1914": "N", "1922": "NONE", "1926": "N", "1929": "NONE", "1932": "S", "1933": "NONE", "1936": "W", "1937": "NONE", "1940": "E", "1941": "NONE", "1942": "S", "1972": "NONE", "1973": "W", "1976": "NONE", "1977": "S", "1982": "NONE", "1983": "N", "1984": "NONE", "1986": "E", "1989": "NONE", "1990": "N", "2021": "NONE", "2022": "E", "2025": "NONE", "2032": "N", "2040": "NONE", "2043": "W", "2044": "N", "2049": "NONE", "2051": "S", "2052": "NONE", "2054": "S", "2055": "NONE", "2056": "W", "2072": "NONE", "2074": "S", "2080": "NONE", "2081": "E", "2083": "NONE", "2087": "N", "2088": "NONE", "2089": "E", "2098": "NONE", "2101": "S", "2102": "NONE", "2108": "S", "2112": "NONE", "2113": "E", "2115": "NONE", "2116": "S", "2143": "NONE", "2145": "W", "2146": "NONE", "2151": "E", "2152": "NONE", "2154": "S", "2158": "NONE", "2159": "N", "2164": "W", "2168": "NONE", "2169": "N", "2172": "NONE", "2173": "S", "2183": "NONE", "2184": "N", "2188": "NONE", "2189": "E", "2190": "NONE", "2191": "N", "2204": "NONE", "2209": "N", "2214": "NONE", "2223": "W", "2224": "NONE", "2225": "E", "2226": "NONE", "2234": "N", "2242": "NONE", "2246": "N", "2248": "NONE", "2261": "N", "2265": "NONE", "2268": "W", "2276": "NONE", "2278": "W", "2284": "NONE", "2286": "E", "2299": "NONE", "2300": "S", "2336": "NONE", "2339": "S", "2341": "W", "2342": "NONE", "2343": "N", "2344": "NONE", "2347": "E", "2350": "NE", "2351": "N", "2383": "NONE", "2387": "E", "2390": "NONE", "2391": "S", "2394": "NONE", "2397": "W", "2399": "NONE", "2403": "W", "2404": "NONE", "2405": "N", "2406": "NONE", "2407": "W", "2408": "NONE", "2412": "N", "2413": "NONE", "2415": "N", "2416": "NONE", "2418": "W", "2422": "S", "2424": "E", "2427": "S", "2458": "W", "2462": "S", "2466": "NONE", "2467": "N", "2468": "NONE", "2469": "E", "2471": "NONE", "2472": "N", "2477": "NONE", "2478": "E", "2480": "N", "2504": "NONE", "2507": "E", "2510": "NONE", "2512": "N", "2513": "NONE", "2514": "N", "2515": "NONE", "2516": "S", "2518": "NONE", "2520": "W", "2526": "NONE", "2528": "N", "2529": "NONE", "2530": "W", "2533": "NONE", "2534": "N", "2536": "W", "2548": "NONE", "2551": "W", "2556": "N", "2561": "NONE", "2563": "S", "2566": "NONE", "2567": "E", "2578": "NONE", "2581": "S", "2583": "SW", "2590": "W", "2595": "NONE", "2598": "E", "2599": "NONE", "2600": "S", "2613": "NONE", "2617": "N", "2621": "NONE", "2623": "E", "2630": "NONE", "2631": "S", "2634": "NONE", "2637": "S", "2649": "NONE", "2653": "S", "2654": "NONE", "2656": "E", "2657": "NONE", "2660": "S", "2661": "NONE", "2663": "N", "2664": "W", "2668": "NONE", "2670": "S", "2671": "NONE", "2672": "N", "2673": "NONE", "2675": "N", "2683": "E", "2684": "NONE", "2685": "N", "2693": "NONE", "2695": "W", "2696": "NONE", "2697": "W", "2699": "NONE", "2703": "W", "2705": "NONE", "2707": "N", "2708": "NONE", "2714": "E", "2720": "S", "2737": "NONE", "2738": "W", "2739": "NONE", "2740": "S", "2741": "NONE", "2742": "N", "2743": "NONE", "2745": "E", "2746": "NONE", "2747": "N", "2766": "NONE", "2769": "N", "2770": "NONE", "2771": "W", "2772": "S", "2774": "NONE", "2775": "W", "2782": "NONE", "2784": "N", "2787": "W", "2791": "E", "2795": "NONE", "2797": "N", "2814": "NONE", "2815": "E", "2824": "NONE", "2826": "S", "2835": "NONE", "2836": "E", "2842": "NONE", "2843": "S", "2848": "NONE", "2851": "E", "2852": "S", "2867": "NONE", "2868": "S", "2879": "NONE", "2880": "W", "2883": "S", "2888": "E"}, "last_tick": 2888, "result": {"color": "BLUE", "p": [23, 31, 0], "score": 120, "tick": 2889}}