{"seed": 0, "moves": {"1": "S", "3": "SW", "11": "W", "25": "S", "29": "SW", "31": "W", "33": "NW", "37": "N", "41": "E", "43": "NE", "45": "E", "49": "S", "53": "W", "55": "NONE", "57": "N", "59": "S", "65": "E", "67": "NE", "75": "N", "77": "NW", "83": "N", "93": "W", "95": "E", "99": "W", "101": "S", "105": "E", "111": "N", "113": "E", "115": "W", "117": "S", "121": "SE", "125": "E", "129": "N", "135": "S", "137": "W", "139": "NONE", "141": "S", "145": "E", "149": "NE", "155": "E", "159": "NE", "165": "E", "167": "W", "171": "E", "173": "S", "177": "W", "183": "N", "185": "W", "187": "NW", "189": "W", "193": "S", "197": "E", "199": "NONE", "201": "S", "205": "SW", "207": "W", "209": "N", "211": "NW", "213": "N", "217": "E", "219": "N", "221": "E", "225": "S", "229": "E", "237": "S", "241": "W", "243": "E", "247": "W", "249": "N", "253": "W", "263": "NONE", "265": "S", "269": "SE", "271": "S", "281": "W", "283": "E", "287": "W", "289": "N", "297": "NE", "307": "N", "309": "W", "311": "N", "313": "W", "317": "S", "321": "E", "323": "NONE", "325": "E", "339": "SE", "345": "E", "347": "NE", "355": "E", "367": "SE", "373": "E", "377": "N", "379": "E", "381": "NE", "383": "N", "385": "W", "389": "N", "397": "E", "401": "N", "403": "S", "407": "N", "409": "W", "413": "S", "423": "NONE", "425": "E", "427": "W", "433": "NW", "435": "W", "445": "S", "447": "N", "451": "S", "453": "E", "463": "NE", "469": "E", "473": "SE", "479": "E", "485": "N", "493": "W", "497": "N", "501": "E", "503": "N", "505": "E", "509": "S", "511": "E", "513": "S", "517": "W", "521": "N", "523": "NONE", "525": "N", "531": "NW", "537": "N", "539": "S", "543": "N", "545": "E", "549": "SE", "551": "S", "557": "W", "561": "S", "565": "SE", "571": "E", "573": "NE", "579": "N", "581": "W", "585": "S", "587": "NONE", "589": "E", "591": "W", "597": "N", "601": "NE", "605": "E", "609": "SE", "615": "E", "625": "N", "627": "S", "631": "N", "633": "W", "637": "S", "643": "E", "645": "S", "647": "N", "649": "W", "653": "S", "655": "W", "657": "S", "661": "E", "667": "W", "669": "N", "671": "NONE", "673": "S", "675": "NONE", "677": "N", "679": "NONE", "681": "W", "685": "SW", "687": "W"}, "last_tick": 687, "result": {"color": "BLUE", "p": [16, 16, 0], "score": 3300, "tick": 700}}