{"seed": 698077464, "moves": {"1": "S", "5": "NONE", "6": "W", "8": "NONE", "10": "W", "15": "NONE", "22": "S", "25": "SW", "26": "W", "30": "S", "34": "SW", "35": "W", "38": "NONE", "40": "N", "45": "W", "47": "WS", "48": "S", "53": "SW", "54": "W", "60": "S", "64": "N", "67": "NONE", "68": "S", "97": "SE", "98": "E", "103": "ES", "104": "S", "108": "SE", "109": "E", "114": "N", "119": "W", "121": "WS", "122": "S", "126": "SE", "127": "E", "137": "NONE", "138": "S", "141": "E", "155": "NONE", "156": "N", "159": "NE", "160": "E", "167": "EN", "168": "N", "172": "NW", "173": "W", "177": "WS", "178": "S", "182": "N", "194": "NONE", "195": "E", "202": "EN", "203": "N", "216": "NW", "217": "W", "221": "N", "227": "NW", "228": "W", "232": "WN", "233": "N", "237": "NE", "238": "E", "241": "ES", "242": "S", "246": "SE", "247": "E", "248": "W", "257": "S", "261": "W", "266": "WS", "267": "S", "271": "NONE", "272": "S", "278": "W", "280": "WS", "281": "S", "286": "NONE", "287": "W", "290": "NONE", "293": "S", "294": "SE", "295": "E", "299": "EN", "300": "N", "305": "NW", "306": "W", "312": "S", "315": "W", "317": "NONE", "319": "S", "325": "SW", "326": "W", "344": "WS", "345": "S", "358": "W"}, "last_tick": 358, "result": {"color": "BLUE", "p": [2, 26, 0], "score": 2140, "tick": 360}}