{"seed": 0, "moves": {"1": "N", "17": "E", "21": "NE", "29": "N", "33": "NW", "51": "N", "53": "NE", "75": "E", "77": "SE", "89": "E", "93": "SE", "101": "S", "107": "SW", "133": "S", "135": "SE", "151": "S", "153": "SW", "161": "S", "165": "SE", "169": "E", "193": "N", "197": "W", "201": "NW", "231": "N", "235": "NE", "259": "SE", "265": "S", "267": "SW", "279": "S", "281": "SE", "319": "E", "321": "NE", "331": "N", "337": "W", "341": "NW", "367": "N", "369": "NE", "387": "N", "405": "W", "409": "S", "413": "SW", "427": "S", "429": "SE", "441": "S", "445": "SW", "449": "W", "451": "NW", "481": "W", "483": "SW", "503": "NW", "515": "N", "517": "E", "521": "NE", "527": "E", "529": "SE", "535": "NE", "543": "E", "553": "S", "557": "SE", "559": "E", "561": "NE", "579": "N", "581": "NW", "587": "W", "605": "N", "607": "E"}, "last_tick": 607, "result": {"color": "BLUE", "p": [30, 1, 0], "score": 2380, "tick": 626}}