{"seed": 0, "moves": {"0": "N", "4": "S", "12": "E", "14": "W", "16": "N", "20": "W", "26": "S", "32": "W", "38": "S", "43": "E", "54": "W", "56": "N", "70": "W", "90": "S", "94": "W", "96": "S", "100": "E", "130": "W", "132": "S", "134": "W", "136": "S", "148": "W", "168": "N", "172": "W", "178": "N", "188": "E", "216": "N", "220": "E", "222": "S", "228": "W", "232": "S", "244": "W", "248": "N", "252": "W", "254": "N", "260": "W", "264": "N", "268": "E", "280": "N", "286": "S", "296": "E", "300": "S", "310": "E", "314": "N", "318": "E", "324": "N", "330": "W", "342": "N", "348": "W", "350": "N", "352": "S", "354": "E", "358": "S", "378": "E", "398": "N", "402": "E", "406": "N", "408": "E", "410": "N", "415": "W", "442": "N", "456": "E", "478": "S", "486": "E", "492": "S", "495": "W", "521": "S", "526": "W", "528": "S", "530": "W", "532": "S", "535": "N", "538": "E", "540": "N", "562": "E", "568": "S", "572": "E", "578": "S", "588": "W", "602": "S", "611": "W", "613": "S", "615": "W", "617": "S", "636": "W", "640": "N", "644": "W", "646": "N", "653": "E", "662": "N", "676": "W", "680": "S", "685": "W", "688": "S", "689": "E", "698": "S", "700": "E", "704": "S", "706": "N", "708": "W", "712": "N", "728": "W", "748": "S", "752": "W", "758": "S", "768": "E", "798": "S", "804": "W", "808": "S", "816": "W", "836": "N", "840": "W", "846": "N", "856": "E", "883": "N", "886": "E", "888": "N", "890": "E", "894": "N", "902": "E", "906": "S", "910": "E", "912": "S", "919": "W", "932": "E", "934": "N", "936": "S", "942": "W", "944": "E", "948": "S", "960": "E", "964": "N", "970": "E", "975": "N", "979": "W", "989": "N", "992": "W", "994": "S", "1006": "W", "1008": "S", "1014": "E", "1038": "N", "1042": "E", "1048": "N", "1058": "W", "1084": "S", "1094": "W", "1096": "N", "1108": "W", "1110": "N", "1122": "E", "1146": "S", "1150": "E", "1151": "S", "1156": "E", "1158": "S", "1162": "W", "1172": "N", "1186": "E"}, "last_tick": 1186, "result": {"tick": 1194}}