{"seed": 0, "moves": {"0": "E", "6": "N", "17": "S", "19": "E", "27": "N", "29": "E", "33": "S", "35": "W", "43": "S", "55": "W", "59": "N", "71": "E", "73": "W", "75": "S", "87": "E", "91": "N", "103": "E", "111": "N", "113": "E", "116": "S", "120": "E", "124": "S", "130": "N", "132": "W", "136": "S", "138": "E", "140": "S", "144": "N", "150": "E", "152": "N", "154": "E", "174": "S", "176": "E", "180": "N", "197": "W", "215": "N", "217": "W", "225": "S", "227": "E", "236": "N", "238": "E", "300": "N", "305": "W", "307": "S", "309": "E", "313": "N", "315": "W", "317": "N", "321": "E", "327": "N", "331": "E", "343": "N", "345": "E", "352": "S", "358": "E", "378": "S", "426": "E", "438": "W", "440": "N", "442": "S", "444": "W", "446": "N", "450": "E", "456": "S", "460": "N", "466": "E", "468": "N", "498": "E", "500": "N", "507": "W", "511": "S", "513": "W", "515": "N", "521": "E", "527": "W", "533": "S", "539": "E", "543": "S", "545": "W", "547": "S", "549": "W", "551": "N", "553": "W", "555": "N", "563": "W", "566": "S", "605": "E", "609": "N", "617": "E", "623": "S", "637": "E", "641": "N", "649": "E", "653": "S", "657": "E", "659": "S", "665": "W", "673": "E", "681": "N", "689": "E", "691": "N", "721": "E", "723": "N", "730": "W", "734": "S", "736": "E", "738": "S", "742": "E", "755": "N", "759": "E", "771": "N", "773": "E", "778": "S", "780": "E", "782": "S", "786": "E", "808": "W", "812": "N", "816": "W", "818": "S", "828": "E", "830": "N", "834": "E", "842": "S", "853": "E", "857": "S", "867": "W", "871": "S", "875": "W", "881": "S", "885": "W", "893": "N", "897": "W", "901": "S", "905": "W", "911": "N", "919": "E", "921": "W", "923": "S", "931": "E", "937": "N", "941": "E", "945": "S", "949": "E", "957": "N", "961": "E", "967": "N", "971": "E", "975": "N", "1038": "W", "1040": "S", "1042": "W", "1044": "N", "1046": "W", "1048": "S", "1050": "W", "1056": "E", "1058": "S", "1071": "N", "1073": "E", "1075": "S", "1077": "E", "1079": "S", "1106": "E", "1110": "N", "1114": "S", "1118": "W", "1122": "N", "1128": "E", "1130": "N", "1132": "E", "1134": "N", "1140": "E", "1147": "S", "1153": "E", "1175": "S", "1177": "E", "1181": "S", "1192": "E", "1196": "S", "1206": "W", "1234": "N", "1238": "E", "1240": "S", "1246": "E", "1248": "S", "1250": "E", "1268": "S", "1272": "E", "1274": "N", "1278": "E", "1282": "N", "1296": "W", "1300": "N", "1310": "E", "1314": "N", "1357": "W", "1359": "S", "1361": "W", "1363": "N", "1365": "W", "1367": "S", "1369": "W", "1375": "N", "1384": "S", "1390": "E", "1392": "S", "1403": "E", "1405": "S", "1407": "E", "1415": "N", "1422": "W", "1426": "S", "1428": "E", "1430": "S", "1434": "E", "1439": "N"}, "last_tick": 1439, "result": {"tick": 1445}}