{"seed": 0, "moves": {"0": "N", "4": "E", "6": "N", "16": "W", "22": "N", "24": "W", "26": "N", "30": "W", "32": "E", "34": "N", "38": "W", "42": "S", "60": "N", "70": "W", "74": "E", "78": "N", "88": "W", "98": "S", "100": "W", "107": "E", "113": "N", "117": "E", "119": "N", "121": "S", "123": "E", "131": "N", "137": "W", "139": "N", "143": "E", "145": "W", "149": "N", "151": "W", "153": "E", "155": "S", "159": "W", "164": "S", "166": "N", "168": "W", "174": "N", "176": "W", "184": "S", "186": "W", "188": "S", "190": "N", "192": "E", "196": "N", "198": "E", "202": "S", "208": "W", "212": "N", "214": "S", "223": "E", "231": "W", "233": "S", "235": "W", "237": "S", "239": "E", "241": "W", "243": "S", "253": "W", "255": "S", "257": "E", "259": "S", "265": "W", "267": "S", "269": "W", "275": "N", "277": "S", "279": "E", "285": "N", "287": "E", "289": "N", "295": "E", "299": "S", "301": "E", "303": "NE", "305": "E", "312": "S", "316": "E", "318": "W", "320": "S", "322": "W", "332": "N", "338": "W", "340": "N", "342": "E", "346": "N", "350": "S", "354": "E", "358": "S", "360": "E", "362": "N", "379": "W", "381": "E", "389": "S", "391": "N", "393": "W", "399": "S", "409": "E", "415": "N", "417": "E", "429": "N", "431": "E", "433": "N", "437": "S", "441": "W", "443": "S", "447": "E", "455": "S", "457": "E", "470": "W", "476": "N", "480": "W", "484": "N", "486": "W", "490": "N", "492": "W", "498": "S", "504": "N", "506": "E", "512": "S", "516": "W", "530": "E", "538": "N", "573": "W", "575": "S", "579": "E", "581": "S", "583": "E", "587": "N", "595": "W", "599": "S", "601": "W", "603": "N", "605": "E", "607": "N", "609": "W", "614": "N", "616": "S", "618": "E", "622": "N", "632": "E", "634": "W", "636": "S", "640": "E", "644": "N", "648": "E", "650": "W", "652": "N", "656": "W", "658": "N", "660": "E", "670": "S", "672": "E", "678": "N", "680": "W", "682": "N", "686": "W", "688": "S", "692": "E", "694": "S", "696": "W", "700": "N", "702": "W", "704": "S", "706": "E", "714": "N", "716": "E", "718": "N", "720": "E", "722": "N", "724": "E", "726": "W", "728": "S", "734": "E", "738": "N", "740": "E", "749": "S", "765": "E", "767": "S", "771": "W", "773": "N", "780": "W", "785": "S", "787": "W", "795": "S", "797": "W", "801": "N", "811": "W", "815": "N", "819": "W", "823": "S", "825": "N", "827": "W", "829": "S", "831": "W", "833": "N", "844": "S", "846": "W", "848": "E", "850": "S", "855": "W", "860": "S", "865": "W", "869": "S", "875": "W", "879": "S", "881": "E", "885": "W", "889": "S", "893": "E", "899": "N", "909": "W", "911": "N", "914": "E", "928": "S", "930": "E", "932": "N", "940": "S", "946": "W", "958": "N", "962": "E", "964": "N", "966": "E", "968": "N", "970": "E", "978": "S", "980": "E", "982": "N", "993": "S", "995": "E", "999": "N", "1003": "W", "1007": "N", "1009": "W", "1013": "S", "1015": "E", "1021": "W", "1023": "S", "1027": "E", "1031": "N", "1041": "W", "1043": "N", "1045": "E", "1047": "S", "1049": "E", "1051": "N", "1057": "W", "1059": "E", "1061": "S", "1064": "E", "1066": "S", "1068": "E", "1082": "S", "1087": "E", "1091": "S", "1097": "W", "1099": "N", "1101": "W", "1109": "S", "1111": "W", "1113": "S", "1115": "W", "1124": "S", "1130": "E", "1138": "N", "1142": "W", "1145": "E", "1147": "S", "1155": "W", "1159": "N", "1168": "E", "1170": "N", "1172": "W", "1188": "E", "1196": "S", "1198": "W", "1200": "E", "1202": "S", "1208": "W", "1210": "N", "1212": "E", "1220": "S", "1226": "E", "1228": "S", "1236": "W", "1240": "S", "1245": "E", "1247": "S", "1249": "E", "1258": "W", "1268": "N", "1270": "W", "1276": "N", "1292": "W", "1300": "N", "1308": "W", "1310": "S", "1314": "W", "1322": "N", "1326": "E", "1328": "N", "1330": "W", "1336": "E", "1340": "S", "1346": "E", "1355": "N", "1363": "W", "1365": "N", "1369": "E", "1371": "S", "1377": "E", "1379": "S", "1381": "W", "1385": "E", "1387": "N", "1391": "W", "1395": "S", "1397": "W", "1399": "S", "1403": "E", "1405": "N", "1420": "S", "1422": "E", "1426": "N", "1430": "W", "1436": "N", "1438": "W", "1444": "S", "1448": "E", "1452": "N", "1454": "E", "1456": "N", "1458": "W", "1466": "S", "1468": "W", "1470": "N", "1484": "E", "1486": "W", "1488": "S", "1498": "W", "1500": "S", "1513": "W", "1515": "S", "1531": "E", "1537": "S", "1541": "W", "1543": "S", "1547": "E", "1549": "N", "1555": "W", "1557": "N", "1559": "E", "1577": "S", "1579": "E", "1581": "N", "1583": "W", "1585": "N", "1587": "E", "1593": "S", "1595": "E", "1597": "N", "1635": "S", "1637": "E", "1641": "N", "1645": "W", "1651": "N", "1653": "W", "1659": "S", "1663": "E", "1667": "N", "1669": "E", "1671": "N", "1673": "W", "1681": "S", "1683": "W", "1685": "N", "1695": "E", "1697": "N", "1699": "E", "1709": "W", "1713": "N", "1715": "S", "1717": "W", "1742": "N", "1744": "S", "1746": "E", "1750": "N", "1752": "S", "1754": "E", "1756": "S"}, "last_tick": 1756, "result": {"tick": 1758}}