{"seed": 0, "moves": {"0": "W", "4": "N", "10": "S", "16": "W", "20": "N", "26": "S", "32": "W", "36": "N", "40": "W", "42": "N", "44": "S", "50": "W", "54": "N", "60": "W", "62": "S", "68": "W", "72": "N", "78": "S", "81": "W", "85": "N", "90": "S", "96": "W", "100": "N", "106": "S", "112": "W", "116": "N", "122": "W", "124": "S", "130": "W", "134": "N", "140": "S", "146": "W", "152": "N", "158": "E", "160": "W", "162": "S", "168": "W", "172": "N", "178": "S", "184": "W", "188": "N", "194": "W", "196": "E", "198": "S", "201": "W", "203": "E", "204": "W", "210": "N", "216": "S", "222": "E", "229": "W", "230": "E", "256": "N", "262": "W", "264": "E", "266": "S", "269": "E", "272": "N", "278": "S", "284": "E", "296": "N", "302": "E", "304": "S", "307": "E", "310": "N", "316": "S", "322": "E", "328": "N", "334": "W", "336": "S", "342": "E", "349": "W", "374": "N", "380": "S", "386": "W", "396": "N", "402": "W", "404": "S", "410": "W", "432": "N", "438": "S", "444": "W", "460": "N", "466": "S", "472": "W", "498": "N", "504": "W", "506": "S", "512": "W", "527": "E", "528": "W", "530": "N", "536": "E", "538": "S", "544": "E", "545": "W", "546": "E", "547": "W", "548": "E", "549": "W", "552": "N", "558": "E", "560": "S", "566": "E", "567": "W", "568": "E", "569": "W", "570": "E", "571": "W", "572": "E", "573": "W", "574": "E", "602": "N", "608": "S", "614": "W", "622": "N", "628": "W", "630": "S", "633": "W", "651": "E", "652": "W", "662": "N", "668": "S", "674": "E", "685": "W", "694": "N", "700": "E", "702": "S", "708": "E", "715": "W", "716": "E", "717": "W", "718": "E", "719": "W", "720": "E", "726": "N", "732": "E", "734": "S", "740": "E", "746": "N", "752": "W", "754": "E", "756": "S", "759": "E", "768": "N", "774": "S", "780": "W", "805": "E", "810": "N", "816": "S", "822": "E", "826": "N", "832": "E", "834": "S", "840": "W", "870": "N", "876": "S", "882": "E", "888": "N", "894": "W", "896": "S", "902": "E", "919": "W", "920": "E", "944": "N", "950": "E", "952": "W", "954": "S", "957": "W", "960": "N", "966": "S", "972": "E", "990": "N", "996": "S", "1002": "E", "1010": "N", "1016": "S", "1022": "E", "1040": "N", "1046": "W", "1048": "E", "1050": "S", "1053": "E", "1056": "N", "1062": "S", "1068": "W", "1079": "E", "1080": "W", "1081": "E", "1082": "W", "1083": "E", "1084": "W", "1085": "E", "1086": "W", "1087": "E", "1088": "W", "1089": "N", "1094": "W", "1096": "S", "1102": "W", "1128": "N", "1134": "S", "1140": "E", "1144": "N", "1150": "S", "1156": "E", "1181": "W", "1182": "E", "1183": "W", "1184": "E", "1185": "W", "1202": "N", "1208": "S", "1214": "E", "1231": "W", "1232": "E", "1248": "N", "1254": "W", "1256": "S", "1262": "E", "1286": "N", "1292": "S", "1298": "W", "1302": "N", "1308": "S", "1314": "E", "1339": "W", "1340": "E", "1341": "W", "1342": "E", "1343": "W", "1344": "E", "1345": "W", "1346": "E", "1347": "W", "1368": "N", "1374": "S", "1380": "W", "1384": "N", "1390": "W", "1392": "S", "1398": "E", "1414": "N", "1420": "W", "1422": "S", "1428": "E", "1442": "N", "1448": "W", "1450": "E", "1452": "S", "1455": "W", "1457": "E", "1458": "N", "1464": "S", "1470": "W", "1476": "N", "1482": "S", "1488": "E", "1495": "W", "1496": "E", "1497": "W", "1498": "E", "1499": "W", "1506": "N", "1512": "S", "1518": "W", "1526": "N", "1532": "S", "1538": "E", "1542": "N", "1548": "S", "1554": "W", "1570": "N", "1576": "S", "1582": "W", "1602": "N", "1608": "W", "1610": "S", "1616": "E", "1626": "N", "1632": "S", "1638": "E", "1654": "N", "1660": "S", "1666": "W", "1678": "N", "1684": "S", "1690": "E", "1694": "N", "1700": "S", "1706": "W", "1718": "N", "1724": "S", "1730": "W", "1742": "N", "1748": "E", "1750": "S", "1756": "W", "1763": "E", "1764": "W", "1765": "N", "1770": "S", "1776": "E", "1777": "W", "1778": "E", "1782": "N", "1788": "S", "1794": "E", "1808": "N", "1814": "S", "1820": "W", "1824": "N", "1830": "S", "1836": "E", "1850": "N", "1856": "E", "1858": "S", "1864": "W", "1884": "N", "1890": "W", "1892": "S", "1895": "W", "1903": "E", "1904": "N", "1910": "S", "1916": "W", "1917": "E", "1918": "W", "1919": "E", "1920": "W", "1922": "N", "1928": "E", "1930": "S", "1933": "E", "1934": "W", "1935": "E", "1956": "N", "1962": "S", "1968": "W", "1989": "E", "1990": "W", "1991": "E", "1992": "W", "1993": "E", "1994": "W", "2012": "N", "2018": "S", "2024": "E", "2042": "S"}, "last_tick": 2042, "result": {"tick": 2046}}