{"seed": 0, "moves": {"0": "E", "2": "N", "8": "W", "16": "N", "20": "S", "22": "E", "28": "N", "36": "E", "40": "N", "44": "E", "50": "W", "56": "N", "60": "W", "70": "E", "78": "N", "90": "W", "94": "N", "98": "W", "102": "E", "106": "S", "110": "E", "116": "N", "118": "E", "130": "S", "138": "E", "144": "W", "154": "E", "158": "N", "168": "W", "170": "N", "176": "E", "180": "W", "194": "S", "198": "N", "210": "W", "218": "E", "242": "S", "244": "E", "252": "S", "254": "E", "256": "S", "264": "E", "272": "S", "274": "E", "278": "N", "288": "W", "294": "E", "298": "N", "304": "W", "306": "E", "308": "S", "312": "E", "320": "N", "326": "S", "332": "SE", "334": "E", "338": "S", "344": "W", "348": "E", "352": "S", "360": "W", "364": "S", "372": "W", "388": "N", "390": "S", "392": "E", "396": "S", "402": "E", "404": "W", "408": "S", "412": "W", "418": "E", "430": "S", "436": "W", "440": "E", "448": "S", "450": "N", "454": "E", "458": "N", "464": "W", "466": "E", "472": "N", "474": "W", "476": "S", "484": "W", "486": "S", "490": "E", "494": "W", "500": "S", "508": "E", "514": "W", "520": "N", "524": "W", "530": "S", "536": "N", "540": "W", "552": "N", "554": "W", "560": "N", "568": "S", "574": "W", "580": "S", "582": "W", "584": "S", "590": "N", "596": "E", "598": "N", "604": "W", "616": "S", "626": "E", "630": "W", "636": "S", "638": "W"}, "last_tick": 638, "result": {"tick": 644}}