{"seed": 0, "moves": {"0": "E", "4": "N", "12": "W", "18": "E", "24": "S", "32": "E", "38": "N", "43": "W", "46": "S", "52": "W", "55": "E", "58": "N", "68": "W", "72": "S", "76": "W", "82": "E", "88": "N", "93": "E", "96": "S", "100": "E", "104": "S", "113": "W", "116": "S", "120": "W", "124": "N", "126": "W", "136": "N", "147": "E", "150": "W", "152": "S", "162": "E", "172": "S", "175": "E", "178": "N", "182": "E", "186": "N", "190": "E", "198": "S", "200": "E", "204": "W", "208": "N", "210": "W", "218": "N", "222": "E", "226": "N", "234": "W", "236": "E", "238": "S", "246": "W", "258": "N", "262": "W", "278": "S", "282": "W", "286": "S", "290": "W", "292": "E", "294": "S", "306": "E", "318": "S", "320": "N", "322": "E", "326": "N", "330": "E", "342": "N", "346": "E", "348": "W", "350": "N", "354": "E", "362": "S", "364": "E", "368": "N", "370": "E", "374": "S", "378": "E", "380": "N", "384": "W", "390": "S", "392": "W", "396": "N", "398": "W", "406": "S", "410": "W", "422": "S", "428": "W", "440": "N", "448": "E", "455": "W", "462": "S", "470": "E", "482": "N", "488": "E", "500": "N", "505": "E", "512": "N", "518": "S", "526": "E", "530": "N", "532": "E"}, "last_tick": 532, "result": {"tick": 540}}