{"seed": 0, "moves": {"0": "W", "4": "S", "11": "N", "16": "W", "20": "N", "22": "S", "35": "N", "39": "W", "44": "E", "49": "S", "53": "E", "55": "S", "57": "E", "65": "N", "69": "S", "73": "W", "75": "S", "77": "W", "81": "E", "93": "N", "100": "S", "102": "E", "107": "W", "115": "S", "117": "E", "119": "S", "123": "N", "135": "E", "142": "W", "144": "N", "149": "S", "157": "E", "159": "N", "161": "E", "165": "W", "169": "N", "171": "W", "175": "S", "177": "E", "185": "N", "199": "S", "205": "E"}, "last_tick": 205, "result": {"tick": 205}}