{"seed": 0, "moves": {"1": "S", "3": "N", "10": "NONE", "11": "N", "12": "NONE", "13": "N", "14": "NONE", "15": "W", "16": "NONE", "17": "N", "18": "NONE", "19": "W", "20": "NONE", "21": "S", "22": "NONE", "23": "S", "24": "NONE", "25": "S", "26": "NONE", "27": "W", "28": "NONE", "29": "N", "30": "NONE", "31": "W", "32": "NONE", "33": "W", "37": "S", "47": "W", "49": "S", "53": "E", "57": "N", "59": "S", "61": "W", "65": "N", "69": "E", "71": "N", "77": "W", "79": "N", "85": "E", "87": "S", "89": "E", "95": "N", "96": "NONE", "97": "E", "98": "NONE", "99": "E", "100": "NONE", "101": "E", "102": "NONE", "103": "E", "104": "NONE", "105": "E", "106": "NONE", "107": "S", "108": "NONE", "109": "E", "110": "NONE", "111": "E", "117": "S", "127": "E", "129": "S", "133": "W", "137": "N", "139": "S", "141": "E", "145": "N", "149": "W", "151": "N", "157": "E", "159": "N", "165": "W", "167": "S", "169": "W", "179": "S", "183": "W", "191": "S", "197": "W", "203": "S", "207": "W", "209": "N", "213": "E", "221": "N", "227": "W", "231": "N", "233": "W", "239": "N", "249": "W", "251": "N", "255": "W", "261": "N", "263": "W", "265": "N", "275": "S", "277": "E", "279": "W", "281": "S", "293": "E", "295": "N", "297": "E", "303": "NONE", "304": "N", "305": "NONE", "306": "N", "307": "NONE", "308": "E", "309": "NONE", "310": "E", "311": "S", "312": "NONE", "313": "E", "314": "NONE", "315": "N", "316": "NONE", "317": "N", "318": "NONE", "320": "E", "321": "N", "322": "NONE", "324": "E", "325": "NONE", "327": "N", "331": "E", "339": "W", "341": "S", "343": "N", "345": "W", "357": "S", "359": "E", "363": "S", "373": "W", "377": "S", "379": "W", "383": "N", "389": "W", "395": "N", "401": "W", "411": "N", "413": "W", "415": "E", "417": "S", "419": "E", "427": "N", "429": "E", "433": "S", "435": "W", "437": "S", "443": "NONE", "444": "S", "445": "NONE", "446": "S", "447": "NONE", "449": "E", "450": "NONE", "451": "E", "452": "NONE", "453": "E", "454": "NONE", "455": "E", "456": "NONE", "457": "E", "459": "N", "461": "E", "462": "NONE", "464": "E", "466": "N", "467": "NONE", "469": "N", "473": "NONE", "474": "W", "475": "NONE", "477": "E", "479": "N", "481": "S", "495": "W", "497": "N", "501": "W", "507": "S", "515": "W", "521": "S", "527": "W", "531": "S", "537": "W", "539": "S", "543": "E", "549": "S", "553": "E", "555": "N", "559": "W", "567": "N", "571": "E", "573": "N", "583": "W", "585": "N"}, "last_tick": 585, "result": {"tick": 586}}