{"seed": 0, "moves": {"1": "N", "3": "E", "7": "S", "9": "E", "11": "N", "19": "E", "21": "S", "29": "E", "33": "N", "39": "NONE", "41": "N", "49": "E", "61": "S", "63": "E", "65": "N", "69": "E", "73": "N", "87": "W", "89": "S", "97": "W", "99": "N", "107": "W", "111": "S", "113": "E", "115": "S", "117": "W", "119": "S", "121": "E", "123": "S", "125": "W", "127": "S", "129": "E", "132": "NONE", "134": "E", "135": "NONE", "137": "E", "139": "S", "151": "W", "157": "S", "159": "E", "161": "S", "163": "W", "165": "S", "167": "E", "169": "S", "171": "W", "173": "S", "175": "E", "177": "S", "179": "W", "181": "S", "183": "E", "187": "S", "191": "W", "193": "S", "195": "W", "197": "N", "199": "S", "201": "W", "213": "S", "217": "E", "219": "S", "227": "W", "231": "S", "235": "E", "251": "N", "257": "E", "259": "S", "265": "E", "267": "N", "275": "W", "281": "S", "283": "W", "285": "N", "289": "S", "293": "E", "295": "N", "297": "E", "303": "S", "311": "W", "313": "N", "319": "W", "321": "S", "327": "W", "333": "NONE", "349": "E", "351": "N", "362": "S", "366": "W", "382": "N", "386": "W", "396": "S", "398": "W", "402": "N", "404": "W", "408": "N", "416": "E", "418": "N", "422": "W", "434": "N", "436": "W", "438": "S", "440": "W", "444": "S", "452": "E", "454": "N", "456": "E", "458": "S", "464": "W", "466": "S", "468": "NONE", "478": "N", "484": "E", "486": "S", "490": "N", "494": "W", "496": "S", "504": "NONE", "514": "E", "516": "N", "522": "W", "524": "S", "526": "W", "528": "S", "536": "N", "558": "E", "564": "N", "566": "W", "568": "N", "570": "E", "572": "N", "574": "W", "576": "N", "578": "E", "580": "N", "582": "W", "584": "N", "586": "E", "588": "N", "590": "W", "594": "N", "598": "E", "600": "N", "602": "E", "604": "S", "606": "E", "610": "N", "612": "E", "620": "N", "624": "W", "626": "N", "634": "E", "638": "W", "644": "N", "648": "W", "652": "NONE", "653": "W", "657": "S", "661": "W", "663": "S", "665": "E", "669": "S", "673": "W", "675": "N", "677": "W", "679": "S", "681": "W", "685": "N", "687": "E", "689": "N", "691": "W", "693": "N", "695": "E", "697": "N", "699": "W", "701": "N", "703": "E", "707": "NONE", "709": "E", "727": "S", "731": "E", "741": "N", "743": "E", "747": "S", "749": "E", "755": "W", "757": "S", "765": "W", "769": "S", "773": "W", "777": "S", "781": "W", "785": "NONE", "786": "N", "794": "E", "798": "N", "800": "W", "810": "S", "812": "E", "818": "S", "826": "W", "832": "S", "834": "W", "836": "S", "838": "E", "840": "NONE", "842": "S", "844": "W", "846": "S", "848": "W", "856": "N", "862": "W", "864": "S", "872": "E", "874": "S", "876": "W", "878": "S", "882": "E", "884": "N", "886": "NONE", "887": "N", "893": "NONE", "906": "S", "910": "E", "912": "NONE", "914": "E", "918": "N", "920": "E", "922": "N", "924": "E", "926": "S", "930": "NONE", "936": "W", "938": "S", "940": "W", "942": "S", "944": "E", "946": "NONE", "947": "S", "949": "E", "953": "S", "961": "W", "965": "S", "967": "E", "973": "NONE", "974": "N", "976": "E", "978": "S", "980": "E", "982": "NONE", "983": "N", "987": "NONE", "989": "N", "995": "E", "997": "N", "999": "W", "1001": "N", "1003": "E", "1009": "N", "1011": "E", "1015": "S", "1021": "E", "1023": "N", "1031": "W", "1033": "N", "1035": "E", "1037": "N", "1041": "W", "1043": "NONE", "1045": "S", "1047": "NONE", "1048": "N", "1050": "NONE", "1101": "S", "1115": "W", "1117": "NONE", "1119": "W", "1127": "N", "1131": "S", "1137": "W", "1143": "N", "1153": "E", "1155": "N", "1158": "NONE"}, "last_tick": 1158, "result": {"tick": 1161}}