{"seed": 0, "moves": {"1": "N", "3": "W", "5": "S", "7": "W", "9": "S", "11": "E", "27": "S", "49": "W", "53": "N", "71": "W", "75": "S", "97": "E", "117": "W", "137": "N", "159": "E", "163": "S", "181": "E", "185": "N", "207": "E", "217": "W", "219": "S", "225": "E", "229": "N", "241": "W", "243": "NONE", "245": "W", "247": "N", "271": "S", "295": "W", "299": "N", "319": "S", "339": "E", "347": "N", "372": "S", "394": "W", "404": "NONE", "413": "W", "415": "N", "441": "W", "449": "NONE", "450": "E", "454": "NONE", "461": "E", "463": "NONE", "487": "E", "489": "S", "493": "W", "497": "NONE", "641": "W", "643": "N", "661": "W", "669": "NONE", "672": "S", "690": "W", "698": "NONE", "699": "W", "709": "N", "725": "E", "729": "NONE", "732": "S", "734": "N", "736": "E", "740": "N", "742": "NONE", "744": "W", "748": "S", "754": "E", "764": "S", "766": "NONE", "767": "N", "769": "W", "779": "N", "787": "E", "795": "N", "799": "W", "803": "N", "807": "E", "811": "N", "815": "E", "819": "N", "821": "NONE", "822": "E", "826": "N", "828": "NONE", "829": "E", "831": "N", "845": "E", "851": "N", "859": "W", "875": "S", "879": "W", "887": "S", "913": "W", "917": "N", "942": "NONE", "944": "N", "945": "NONE", "947": "N", "948": "NONE"}, "last_tick": 948, "result": {"tick": 951}}